pst/__init__.py
pst/__version__.py
pst/cookbook.py
pst/circulate/PstCirculateInfos.py
pst/circulate/link.py
pst/circulate/p2api.py
pst/circulate/query.py
pst/interface/PstInitGui.py
pst/interface/PstInitSlack.py
pst/interface/pstgui.py
pst/interface/pstslack.py
pst/pipeline/PstGetGalaxies.py
pst/pipeline/PstGetTilings.py
pst/pipeline/PstParseTriggers.py
pst/pipeline/PstPrioritization.py
pst/pipeline/galaxies.py
pst/pipeline/galaxy.py
pst/pipeline/galaxy_old.py
pst/pipeline/prioritization.py
pst/pipeline/query.py
pst/pipeline/tilings.py
pst/pipeline/triggers.py
pst/view/PstPlotter.py
pst/view/pstplot.py
pst/view/show.py
pstools-0.5.1.1.dist-info/LICENSE
pstools-0.5.1.1.dist-info/METADATA
pstools-0.5.1.1.dist-info/WHEEL
pstools-0.5.1.1.dist-info/top_level.txt
pstools-0.5.1.1.dist-info/RECORD
